MANIFEST.in
setup.cfg
setup.py
hud/__init__.py
hud/__main__.py
hud/elements.py
hud/eventHandler.py
hud/hud.py
hud.egg-info/PKG-INFO
hud.egg-info/SOURCES.txt
hud.egg-info/dependency_links.txt
hud.egg-info/entry_points.txt
hud.egg-info/requires.txt
hud.egg-info/top_level.txt
hud/pgu.theme/Roboto-Regular.ttf
hud/pgu.theme/Vera.ttf
hud/pgu.theme/blue.background.png
hud/pgu.theme/box.down.png
hud/pgu.theme/box.normal.png
hud/pgu.theme/button.down.png
hud/pgu.theme/button.normal.last.png
hud/pgu.theme/button.normal.png
hud/pgu.theme/button.on.last.png
hud/pgu.theme/button.on.png
hud/pgu.theme/checkbox.off.normal.png
hud/pgu.theme/checkbox.on.down.png
hud/pgu.theme/checkbox.on.normal.png
hud/pgu.theme/console.input.focus.png
hud/pgu.theme/console.input.normal.png
hud/pgu.theme/console.png
hud/pgu.theme/desktop.png
hud/pgu.theme/dialog.bar.png
hud/pgu.theme/dialog.close.down.png
hud/pgu.theme/dialog.close.normal.png
hud/pgu.theme/dialog.png
hud/pgu.theme/filebrowser.folder.png
hud/pgu.theme/hslider.left.png
hud/pgu.theme/hslider.right.png
hud/pgu.theme/input.focus.png
hud/pgu.theme/input.normal.png
hud/pgu.theme/list.item.normal.png
hud/pgu.theme/list.png
hud/pgu.theme/menu.down.png
hud/pgu.theme/menu.hover.png
hud/pgu.theme/menu.normal.png
hud/pgu.theme/menu.option.hover.png
hud/pgu.theme/menu.option.normal.png
hud/pgu.theme/radio.off.normal.png
hud/pgu.theme/radio.on.down.png
hud/pgu.theme/radio.on.normal.png
hud/pgu.theme/select.arrow.down.png
hud/pgu.theme/select.arrow.normal.png
hud/pgu.theme/select.arrow.png
hud/pgu.theme/select.option.hover.png
hud/pgu.theme/select.option.normal.png
hud/pgu.theme/select.options.png
hud/pgu.theme/select.selected.normal.png
hud/pgu.theme/slider.bar.normal.png
hud/pgu.theme/slider.png
hud/pgu.theme/style.ini
hud/pgu.theme/switch.off.last.png
hud/pgu.theme/switch.off.png
hud/pgu.theme/switch.on.last.png
hud/pgu.theme/switch.on.png
hud/pgu.theme/tool.down.png
hud/pgu.theme/tool.normal.png
hud/pgu.theme/vslider.down.png
hud/pgu.theme/vslider.up.png
hud/pgu.theme/mdi/materialdesignicons-webfont.ttf
hud/pgu.theme/mdi/materialdesignicons.css