Metadata-Version: 1.1
Name: hud
Version: 0.3b2
Summary: Home Assistant UI Display
Home-page: https://github.com/subutux/HUD
Author: Stijn Van Campenhout
Author-email: subutux@gmail.com
License: MIT
Download-URL: https://github.com/subutux/HUD/tarball/0.3b2
Keywords: pygame,rpi,ui,touchscreen,homeassistant
Platform: UNKNOWN
